{
  "info": {
    "name": "近大高専前",
    "to": "名張駅",
    "last_checked_date": "2025-12-04"
  },
  "timetables": {
    "weekdays": {
      "type": "平日時刻表",
      "schedule": {
        "5": [36],
        "6": [16, 41, 56],
        "7": [11, 24, 46, 59],
        "8": [8, 17, 48],
        "9": [9, 34],
        "10": [10, 34],
        "11": [10, 34],
        "12": [10, 34],
        "13": [10, 34],
        "14": [10, 40],
        "15": [10, 40, 54],
        "16": [14, 34, 54],
        "17": [14, 34, 54],
        "18": [14, 34, 37, 54],
        "19": [14, 44],
        "20": [14],
        "21": [9]
      }
    },
    "weekends_holidays": {
      "type": "土日祝日時刻表",
      "schedule": {
        "6": [24, 48],
        "7": [11, 44],
        "8": [14, 49],
        "9": [34],
        "10": [10, 34],
        "11": [10, 34],
        "12": [10, 34],
        "13": [10, 34],
        "14": [10, 34],
        "15": [10, 34],
        "16": [10, 34],
        "17": [10, 34, 37],
        "18": [10, 34],
        "19": [4, 37],
        "20": [9, 39],
        "21": [24]
      }
    }
  }
}
